dekeyrej_plain_pages-0.9.7.dist-info/licenses/LICENSE
plain_pages/__init__.py
plain_pages/displaypage.py
plain_pages/serverpage.py
dekeyrej_plain_pages-0.9.7.dist-info/METADATA
dekeyrej_plain_pages-0.9.7.dist-info/WHEEL
dekeyrej_plain_pages-0.9.7.dist-info/entry_points.txt
dekeyrej_plain_pages-0.9.7.dist-info/top_level.txt
dekeyrej_plain_pages-0.9.7.dist-info/RECORD
